LICENSE
naif_eop_high_prec/__init__.py
naif_eop_high_prec/compare.py
naif_eop_high_prec/earth_latest_high_prec.bpc
naif_eop_high_prec/earth_latest_high_prec.md5
naif_eop_high_prec/fetch.py
naif_eop_high_prec/tests/__init__.py
naif_eop_high_prec/tests/test_compare.py
naif_eop_high_prec/tests/test_naif_eop_high_prec.py
naif_eop_high_prec-2025.10.4.dist-info/licenses/LICENSE
naif_eop_high_prec-2025.10.4.dist-info/METADATA
naif_eop_high_prec-2025.10.4.dist-info/WHEEL
naif_eop_high_prec-2025.10.4.dist-info/top_level.txt
naif_eop_high_prec-2025.10.4.dist-info/RECORD
